findtui-1.3.3.dist-info/entry_points.txt
findtui-1.3.3.dist-info/DESCRIPTION.rst
findtui-1.3.3.dist-info/RECORD
findtui-1.3.3.dist-info/WHEEL
findtui-1.3.3.dist-info/metadata.json
findtui-1.3.3.dist-info/METADATA
findtui-1.3.3.dist-info/top_level.txt
findtui/main.py
findtui/view.py
findtui/options.py
findtui/find_object.py
findtui/model.py
findtui/__init__.py
findtui/tests/test_view.py
findtui/tests/test_model.py
findtui/tests/test_find_object.py
findtui/tests/__init__.py
