Metadata-Version: 2.0
Name: findtui
Version: 1.3.3
Summary: wrap find(1) with terminal UI
Home-page: https://github.com/spacewander/find
Author: spacewander
Author-email: spacewanderlzx@gmail.com
License: MIT
Keywords: find terminal
Platform: UNKNOWN
Classifier: Development Status :: 5 - Production/Stable
Classifier: Intended Audience :: Developers
Classifier: Intended Audience :: System Administrators
Classifier: Environment :: Console
Classifier: Environment :: Console :: Curses
Classifier: License :: OSI Approved :: MIT License
Classifier: Programming Language :: Python :: 2
Classifier: Programming Language :: Python :: 2.7
Classifier: Programming Language :: Python :: 3
Classifier: Programming Language :: Python :: 3.2
Classifier: Programming Language :: Python :: 3.4
Requires-Dist: urwid
